.isort.cfg
CHANGES.rst
MANIFEST.in
Makefile
README.rst
buildout.cfg
ci.cfg
requirements.txt
setup.py
docs/LICENSE.GPL
docs/LICENSE.rst
src/collective/__init__.py
src/collective.eeafaceted.collectionwidget.egg-info/PKG-INFO
src/collective.eeafaceted.collectionwidget.egg-info/SOURCES.txt
src/collective.eeafaceted.collectionwidget.egg-info/dependency_links.txt
src/collective.eeafaceted.collectionwidget.egg-info/entry_points.txt
src/collective.eeafaceted.collectionwidget.egg-info/namespace_packages.txt
src/collective.eeafaceted.collectionwidget.egg-info/not-zip-safe
src/collective.eeafaceted.collectionwidget.egg-info/requires.txt
src/collective.eeafaceted.collectionwidget.egg-info/top_level.txt
src/collective/eeafaceted/__init__.py
src/collective/eeafaceted/collectionwidget/__init__.py
src/collective/eeafaceted/collectionwidget/adapters.py
src/collective/eeafaceted/collectionwidget/categories.py
src/collective/eeafaceted/collectionwidget/config.py
src/collective/eeafaceted/collectionwidget/configure.zcml
src/collective/eeafaceted/collectionwidget/events.py
src/collective/eeafaceted/collectionwidget/events.zcml
src/collective/eeafaceted/collectionwidget/indexes.py
src/collective/eeafaceted/collectionwidget/interfaces.py
src/collective/eeafaceted/collectionwidget/mk_sync_locales.sh
src/collective/eeafaceted/collectionwidget/permissions.zcml
src/collective/eeafaceted/collectionwidget/profiles.zcml
src/collective/eeafaceted/collectionwidget/setuphandlers.py
src/collective/eeafaceted/collectionwidget/testing.zcml
src/collective/eeafaceted/collectionwidget/upgrades.py
src/collective/eeafaceted/collectionwidget/utils.py
src/collective/eeafaceted/collectionwidget/vocabulary.py
src/collective/eeafaceted/collectionwidget/browser/__init__.py
src/collective/eeafaceted/collectionwidget/browser/configure.zcml
src/collective/eeafaceted/collectionwidget/browser/views.py
src/collective/eeafaceted/collectionwidget/browser/static/.gitkeep
src/collective/eeafaceted/collectionwidget/browser/static/collective.eeafaceted.collectionwidget.css
src/collective/eeafaceted/collectionwidget/browser/static/dashboardcollection.png
src/collective/eeafaceted/collectionwidget/browser/templates/category.pt
src/collective/eeafaceted/collectionwidget/browser/templates/term.pt
src/collective/eeafaceted/collectionwidget/content/__init__.py
src/collective/eeafaceted/collectionwidget/content/configure.zcml
src/collective/eeafaceted/collectionwidget/content/dashboardcollection.py
