Metadata-Version: 2.1
Name: collective.eeafaceted.collectionwidget
Version: 1.17
Summary: eea.facetednavigation widget that enables selecting a collection (among several) as base filter
Home-page: http://pypi.python.org/pypi/collective.eeafaceted.collectionwidget
Author: IMIO
Author-email: support@imio.be
License: GPL
Keywords: Plone faceted navigation widget collection
Platform: UNKNOWN
Classifier: Development Status :: 6 - Mature
Classifier: Environment :: Web Environment
Classifier: Framework :: Plone
Classifier: Framework :: Plone :: 4.3
Classifier: Framework :: Plone :: 5.0
Classifier: Framework :: Plone :: 5.1
Classifier: License :: OSI Approved :: GNU General Public License (GPL)
Classifier: Programming Language :: Python
Classifier: Programming Language :: Python :: 2.7
Provides-Extra: test
